{"result":{"Early Spring Elementary School":[{"department_id":"Admin","department_name":"Admin"},{"department_id":"Teaching Staff","department_name":"Teaching Staff"},{"department_id":"None Teaching Staff","department_name":"None Teaching Staff"},{"department_id":"Account","department_name":"Account"},{"department_id":"Transport","department_name":"Transport"}],"Early Spring Nursery School":[{"department_id":"Admin","department_name":"Admin"},{"department_id":"Teaching Staff","department_name":"Teaching Staff"},{"department_id":"None Teaching Staff","department_name":"None Teaching Staff"},{"department_id":"Account","department_name":"Account"},{"department_id":" Transport","department_name":" Transport"},{"department_id":"FOUNDATION","department_name":"FOUNDATION"}],"Early Spring College":[{"department_id":"Admin","department_name":"Admin"},{"department_id":"Teaching Staff","department_name":"Teaching Staff"},{"department_id":"None Teaching Staff","department_name":"None Teaching Staff"},{"department_id":"Account","department_name":"Account"},{"department_id":"Transport","department_name":"Transport"}]}}